deims.py
deims-4.0.dist-info/LICENSE
deims-4.0.dist-info/METADATA
deims-4.0.dist-info/WHEEL
deims-4.0.dist-info/top_level.txt
deims-4.0.dist-info/RECORD
