Metadata-Version: 2.1
Name: deims
Version: 4.0
Summary: Interface to the DEIMS-SDR API
Home-page: https://github.com/eLTER-RI/deimsPy
Author: Christoph Wohner and Will Bolton
Author-email: wilbol@ceh.ac.uk
Classifier: Programming Language :: Python :: 3
Classifier: License :: OSI Approved :: MIT License
Classifier: Operating System :: OS Independent
Requires-Python: >=3
License-File: LICENSE
Requires-Dist: geopandas
Requires-Dist: geopy
Requires-Dist: pandas
